pymend/__init__.py
pymend/__main__.py
pymend/const.py
pymend/file_parser.py
pymend/files.py
pymend/output.py
pymend/py.typed
pymend/pymend.py
pymend/pymendapp.py
pymend/report.py
pymend/types.py
pymend/docstring_parser/__init__.py
pymend/docstring_parser/common.py
pymend/docstring_parser/epydoc.py
pymend/docstring_parser/google.py
pymend/docstring_parser/numpydoc.py
pymend/docstring_parser/parser.py
pymend/docstring_parser/rest.py
pymend/docstring_parser/util.py
pymend-1.1.0.dist-info/METADATA
pymend-1.1.0.dist-info/WHEEL
pymend-1.1.0.dist-info/entry_points.txt
pymend-1.1.0.dist-info/licenses/LICENSE
pymend-1.1.0.dist-info/RECORD
