Metadata-Version: 2.3
Name: pymend
Version: 1.1.0
Summary: Generate, fix and convert docstrings.
Project-URL: Homepage, https://github.com/JanEricNitschke/pymend
Project-URL: Documentation, https://pymend.readthedocs.io/en/latest/
Project-URL: GitHub, https://github.com/JanEricNitschke/pymend
Project-URL: Bug Tracker, https://github.com/JanEricNitschke/pymend/issues
Author-email: Jan-Eric Nitschke <janericnitschke@gmail.com>
Maintainer-email: Jan-Eric Nitschke <janericnitschke@gmail.com>
License: MIT
Keywords: docstring,pymend
Classifier: Intended Audience :: Developers
Classifier: License :: OSI Approved :: MIT License
Classifier: Operating System :: OS Independent
Classifier: Programming Language :: Python :: 3
Classifier: Programming Language :: Python :: 3.9
Classifier: Programming Language :: Python :: 3.10
Classifier: Programming Language :: Python :: 3.11
Classifier: Programming Language :: Python :: 3.12
Classifier: Programming Language :: Python :: 3.13
Classifier: Topic :: Documentation
Requires-Python: >=3.9
Requires-Dist: click>=8.0.0
Requires-Dist: tomli>=1.1.0; python_version < '3.11'
Requires-Dist: typing-extensions<5.0,>=4.0
